pretty_mod-0.2.3.dist-info/METADATA
pretty_mod-0.2.3.dist-info/WHEEL
pretty_mod-0.2.3.dist-info/entry_points.txt
pretty_mod-0.2.3.dist-info/licenses/LICENSE
pretty_mod/__init__.py
pretty_mod/__main__.py
pretty_mod/_pretty_mod.cpython-39-powerpc64le-linux-gnu.so
pretty_mod/_pretty_mod.pyi
pretty_mod/cli.py
pretty_mod/explorer.py
pretty_mod/py.typed
pretty_mod-0.2.3.dist-info/RECORD
