Metadata-Version: 2.4
Name: pretty-mod
Version: 0.2.3
License-File: LICENSE
Summary: A python module tree explorer for LLMs (and humans)
Author-email: zzstoatzz <thrast36@gmail.com>
License: MIT
Requires-Python: >=3.9
